Metadata-Version: 2.1
Name: update-dict
Version: 1.0.3
Summary: Is a method of updating nested dictionaries
Home-page: https://github.com/yutu-75/update_dict.git
Author: yutu-75
Author-email: xiao3952@foxmail.com
License: UNKNOWN
Platform: UNKNOWN
Classifier: Programming Language :: Python :: 3
